one_interfaces/__init__.py
one_interfaces/account_status_pb2.py
one_interfaces/activity_pb2.py
one_interfaces/activity_type_pb2.py
one_interfaces/address_pb2.py
one_interfaces/agency_pb2.py
one_interfaces/analyte_pb2.py
one_interfaces/analyte_result_pb2.py
one_interfaces/analyte_results_import_profile_pb2.py
one_interfaces/analyte_results_import_telemetry_pb2.py
one_interfaces/apierror_pb2.py
one_interfaces/apiresponse_pb2.py
one_interfaces/auditevent_pb2.py
one_interfaces/cell_monitor_backup_pb2.py
one_interfaces/cell_pb2.py
one_interfaces/celldata_binding_pb2.py
one_interfaces/celldata_pb2.py
one_interfaces/cells_pb2.py
one_interfaces/cellvalue_backup_pb2.py
one_interfaces/claros_i18nkey_text_reference_pb2.py
one_interfaces/claros_jsonTicksDateTime_pb2.py
one_interfaces/claros_key_value_pb2.py
one_interfaces/client_pb2.py
one_interfaces/cloud_event_pb2.py
one_interfaces/coagmeasurement_pb2.py
one_interfaces/column_pb2.py
one_interfaces/computation_binding_pb2.py
one_interfaces/computation_execution_pb2.py
one_interfaces/computation_pb2.py
one_interfaces/computation_variable_binding_pb2.py
one_interfaces/configuration_note_pb2.py
one_interfaces/configuration_pb2.py
one_interfaces/configuration_tag_pb2.py
one_interfaces/content_pb2.py
one_interfaces/csv_configuration_file_pb2.py
one_interfaces/data_source_binding_pb2.py
one_interfaces/data_source_configuration_pb2.py
one_interfaces/delphi_configuration_execution_pb2.py
one_interfaces/delphi_details_parameter_pb2.py
one_interfaces/delphi_execution_parameter_pb2.py
one_interfaces/delphi_model_details_pb2.py
one_interfaces/delphi_model_execution_pb2.py
one_interfaces/delphi_scenario_configuration_pb2.py
one_interfaces/digital_twin_column_telemetry_propertybag_pb2.py
one_interfaces/digital_twin_enterprise_data_telemetry_pb2.py
one_interfaces/digital_twin_instrument_telemetry_propertybag_pb2.py
one_interfaces/digital_twin_pb2.py
one_interfaces/digital_twin_subtype_pb2.py
one_interfaces-7.12.0.dist-info/LICENSE.txt
one_interfaces-7.12.0.dist-info/METADATA
one_interfaces-7.12.0.dist-info/WHEEL
one_interfaces-7.12.0.dist-info/top_level.txt
one_interfaces-7.12.0.dist-info/RECORD
